fastsparsegams/__init__.py
fastsparsegams/fastsparsegams.cpython-38-x86_64-linux-gnu.so
fastsparsegams/interface.py
fastsparsegams/models.py
fastsparsegams/version.py
fastsparsegams/include/armadillo
fastsparsegams/include/armadillo_bits/BaseCube_bones.hpp
fastsparsegams/include/armadillo_bits/BaseCube_meat.hpp
fastsparsegams/include/armadillo_bits/Base_bones.hpp
fastsparsegams/include/armadillo_bits/Base_meat.hpp
fastsparsegams/include/armadillo_bits/Col_bones.hpp
fastsparsegams/include/armadillo_bits/Col_meat.hpp
fastsparsegams/include/armadillo_bits/CubeToMatOp_bones.hpp
fastsparsegams/include/armadillo_bits/CubeToMatOp_meat.hpp
fastsparsegams/include/armadillo_bits/Cube_bones.hpp
fastsparsegams/include/armadillo_bits/Cube_meat.hpp
fastsparsegams/include/armadillo_bits/GenCube_bones.hpp
fastsparsegams/include/armadillo_bits/GenCube_meat.hpp
fastsparsegams/include/armadillo_bits/Gen_bones.hpp
fastsparsegams/include/armadillo_bits/Gen_meat.hpp
fastsparsegams/include/armadillo_bits/GlueCube_bones.hpp
fastsparsegams/include/armadillo_bits/GlueCube_meat.hpp
fastsparsegams/include/armadillo_bits/Glue_bones.hpp
fastsparsegams/include/armadillo_bits/Glue_meat.hpp
fastsparsegams/include/armadillo_bits/MapMat_bones.hpp
fastsparsegams/include/armadillo_bits/MapMat_meat.hpp
fastsparsegams/include/armadillo_bits/Mat_bones.hpp
fastsparsegams/include/armadillo_bits/Mat_meat.hpp
fastsparsegams/include/armadillo_bits/OpCube_bones.hpp
fastsparsegams/include/armadillo_bits/OpCube_meat.hpp
fastsparsegams/include/armadillo_bits/Op_bones.hpp
fastsparsegams/include/armadillo_bits/Op_meat.hpp
fastsparsegams/include/armadillo_bits/Proxy.hpp
fastsparsegams/include/armadillo_bits/ProxyCube.hpp
fastsparsegams/include/armadillo_bits/Row_bones.hpp
fastsparsegams/include/armadillo_bits/Row_meat.hpp
fastsparsegams/include/armadillo_bits/SizeCube_bones.hpp
fastsparsegams/include/armadillo_bits/SizeCube_meat.hpp
fastsparsegams-0.2.0.dist-info/LICENSE
fastsparsegams-0.2.0.dist-info/METADATA
fastsparsegams-0.2.0.dist-info/WHEEL
fastsparsegams-0.2.0.dist-info/top_level.txt
fastsparsegams-0.2.0.dist-info/RECORD
