Metadata-Version: 2.1
Name: fastsparsegams
Version: 0.2.0
Summary: fastSparseGAMs is a Python package that offers an efficient framework for solving L0-regularized learning problems in sparse generalized additive models (GAMs). Leveraging the L0Learn package, this package introduces two novel algorithms, namely quadratic cuts and dynamic feature ordering, to deliver faster computational speed. Additionally, it comes with a new loss function (exponential loss) for classification.
Home-page: https://github.com/tynanseltzer/L0Learn
Author: Jiachang Liu
Author-email: jiachang.liu@duke.edu
Maintainer: Tynan Seltzer
Maintainer-email: tynanseltzer@gmail.com
License: MIT
Project-URL: Source, https://github.com/tynanseltzer/L0Learn
Project-URL: Tracker, https://github.com/tynanseltzer/L0Learn/issues
Classifier: Intended Audience :: Science/Research
Classifier: Intended Audience :: Developers
Classifier: Topic :: Scientific/Engineering :: Mathematics
Classifier: Topic :: Software Development :: Libraries :: Python Modules
Classifier: Development Status :: 4 - Beta
Classifier: Programming Language :: C++
Classifier: Programming Language :: Python :: 3.7
Classifier: Programming Language :: Python :: 3.8
Classifier: Programming Language :: Python :: 3.9
Classifier: Programming Language :: Python :: 3.10
Classifier: Operating System :: POSIX
Classifier: Operating System :: MacOS
Classifier: License :: OSI Approved :: MIT License
Requires-Python: >=3.7
License-File: LICENSE
Requires-Dist: numpy>=1.19.0
Requires-Dist: scipy>=1.0.0
Requires-Dist: pandas>=1.0.0
Requires-Dist: matplotlib
Provides-Extra: all
Requires-Dist: hypothesis; extra == "all"
Provides-Extra: test
Requires-Dist: hypothesis; extra == "test"
